dup_file_finder/__init__.py
dup_file_finder/cli.py
dup_file_finder/core.py
dup_file_finder/py.typed
dup_file_finder/utils.py
dup_file_finder-0.0.3.dist-info/licenses/LICENSE
dup_file_finder-0.0.3.dist-info/METADATA
dup_file_finder-0.0.3.dist-info/WHEEL
dup_file_finder-0.0.3.dist-info/entry_points.txt
dup_file_finder-0.0.3.dist-info/top_level.txt
dup_file_finder-0.0.3.dist-info/RECORD
