Metadata-Version: 2.4
Name: dup-file-finder
Version: 0.0.3
Summary: A Python library to find and manage duplicate files
Author: Tyler Barrus
License: MIT
Project-URL: Homepage, https://github.com/barrust/dup-file-finder
Project-URL: Repository, https://github.com/barrust/dup-file-finder
Project-URL: Bug-tracker, https://github.com/barrust/dup-file-finder/issues
Project-URL: Documentation, https://dup-file-finder.readthedocs.io/
Classifier: License :: OSI Approved :: MIT License
Classifier: Operating System :: OS Independent
Classifier: Programming Language :: Python :: 3
Classifier: Programming Language :: Python :: 3.10
Classifier: Programming Language :: Python :: 3.11
Classifier: Programming Language :: Python :: 3.12
Classifier: Programming Language :: Python :: 3.13
Classifier: Programming Language :: Python :: 3.14
Requires-Python: >=3.10
License-File: LICENSE
Dynamic: license-file
